bottleutils
