Metadata-Version: 1.0
Name: bottleutils
Version: 0.1.5
Summary: Reusable components for bottle
Home-page: https://github.com/BasementCat/bottle-utils
Author: Alec Elton
Author-email: alec.elton@gmail.com
License: UNKNOWN
Platform: UNKNOWN
